[{
  "_id": {
    "$oid": "631d98c4c8406ef6bfc29904"
  },
  "name": "Men Regular Fit Solid Formal Shirt",
  "description": [
    {
      "key": "Pack of",
      "value": "1",
      "_id": {
        "$oid": "6370f1ff49ee88b1ea0ff019"
      }
    },
    {
      "key": "Style Code",
      "value": "sH_65",
      "_id": {
        "$oid": "6370f1ff49ee88b1ea0ff01a"
      }
    },
    {
      "key": "Closure",
      "value": "Button",
      "_id": {
        "$oid": "6370f1ff49ee88b1ea0ff01b"
      }
    },
    {
      "key": "Fit",
      "value": "Regular",
      "_id": {
        "$oid": "6370f1ff49ee88b1ea0ff01c"
      }
    },
    {
      "key": "Fabric",
      "value": "Viscose Rayon",
      "_id": {
        "$oid": "6370f1ff49ee88b1ea0ff01d"
      }
    },
    {
      "key": "Sleeve",
      "value": "Full Sleeve",
      "_id": {
        "$oid": "6370f1ff49ee88b1ea0ff01e"
      }
    },
    {
      "key": "Pattern",
      "value": "Solid",
      "_id": {
        "$oid": "6370f1ff49ee88b1ea0ff01f"
      }
    },
    {
      "key": "Reversible",
      "value": "No",
      "_id": {
        "$oid": "6370f1ff49ee88b1ea0ff020"
      }
    },
    {
      "key": "Color",
      "value": "Light Blue",
      "_id": {
        "$oid": "6370f1ff49ee88b1ea0ff021"
      }
    },
    {
      "key": "Fabric Care",
      "value": "Regular Machine Wash",
      "_id": {
        "$oid": "6370f1ff49ee88b1ea0ff022"
      }
    },
    {
      "key": "Suitable For",
      "value": "Western Wear",
      "_id": {
        "$oid": "6370f1ff49ee88b1ea0ff023"
      }
    },
    {
      "key": "Hem",
      "value": "curved",
      "_id": {
        "$oid": "6370f1ff49ee88b1ea0ff024"
      }
    }
  ],
  "price": 474,
  "images": [
    {
      "public_id": "thisissampleid",
      "url": "https://rukminim1.flixcart.com/image/832/832/l0cr4i80/shirt/m/b/e/xl-sh-65-getchi-original-imagc5xpszdwrruz.jpeg?q=70",
      "_id": {
        "$oid": "6370f1ff49ee88b1ea0ff02a"
      }
    },
    {
      "public_id": "thisissampleid",
      "url": "https://rukminim1.flixcart.com/image/832/832/l0cr4i80/shirt/x/s/v/xl-sh-65-getchi-original-imagc5xpuzkyshxb.jpeg?q=70",
      "_id": {
        "$oid": "6370f1ff49ee88b1ea0ff02b"
      }
    },
    {
      "public_id": "thisissampleid",
      "url": "https://rukminim1.flixcart.com/image/832/832/l0cr4i80/shirt/p/1/j/xl-sh-65-getchi-original-imagc5xprry8tqgp.jpeg?q=70",
      "_id": {
        "$oid": "6370f1ff49ee88b1ea0ff02c"
      }
    },
    {
      "public_id": "thisissampleid",
      "url": "https://rukminim1.flixcart.com/image/832/832/l0cr4i80/shirt/a/y/0/xl-sh-65-getchi-original-imagc5xpydxyx8mk.jpeg?q=70",
      "_id": {
        "$oid": "6370f1ff49ee88b1ea0ff02d"
      }
    }
  ],
  "category": "menswear",
  "stock": 2,
  "numOfReviews": 0,
  "reviews": [],
  "createdAt": {
    "$date": {
      "$numberLong": "1662884036156"
    }
  },
  "__v": 0,
  "brand": "GETCHI",
  "discount": 47,
  "isFeatured": true,
  "mrp": 899,
  "seller": "SheerHeerprints",
  "sellerRating": "4.2",
  "sizes": [
    {
      "size": "S",
      "_id": {
        "$oid": "6370f1ff49ee88b1ea0ff025"
      }
    },
    {
      "size": "M",
      "_id": {
        "$oid": "6370f1ff49ee88b1ea0ff026"
      }
    },
    {
      "size": "L",
      "_id": {
        "$oid": "6370f1ff49ee88b1ea0ff027"
      }
    },
    {
      "size": "XL",
      "_id": {
        "$oid": "6370f1ff49ee88b1ea0ff028"
      }
    },
    {
      "size": "XXL",
      "_id": {
        "$oid": "6370f1ff49ee88b1ea0ff029"
      }
    }
  ],
  "ratings": 4
},{
  "_id": {
    "$oid": "631d98d7c8406ef6bfc2990a"
  },
  "name": "Women A-line Multicolor Dress",
  "description": [
    {
      "key": "Color",
      "value": "Multicolor",
      "_id": {
        "$oid": "6370efb749ee88b1ea0feccd"
      }
    },
    {
      "key": "Length",
      "value": "Midi/Calf Length",
      "_id": {
        "$oid": "6370efb749ee88b1ea0fecce"
      }
    },
    {
      "key": "Fabric",
      "value": "Crepe",
      "_id": {
        "$oid": "6370efb749ee88b1ea0feccf"
      }
    },
    {
      "key": "Pattern",
      "value": "Floral Printn",
      "_id": {
        "$oid": "6370efb749ee88b1ea0fecd0"
      }
    },
    {
      "key": "Ideal For",
      "value": "Women",
      "_id": {
        "$oid": "6370efb749ee88b1ea0fecd1"
      }
    },
    {
      "key": "Type",
      "value": "A-line",
      "_id": {
        "$oid": "6370efb749ee88b1ea0fecd2"
      }
    },
    {
      "key": "Style Code",
      "value": "GR5991",
      "_id": {
        "$oid": "6370efb749ee88b1ea0fecd3"
      }
    },
    {
      "key": "Suitable For",
      "value": "Western Wear",
      "_id": {
        "$oid": "6370efb749ee88b1ea0fecd4"
      }
    },
    {
      "key": "Sleeve Length",
      "value": "Short Sleeve",
      "_id": {
        "$oid": "6370efb749ee88b1ea0fecd5"
      }
    },
    {
      "key": "Neck",
      "value": "Square Neck",
      "_id": {
        "$oid": "6370efb749ee88b1ea0fecd6"
      }
    },
    {
      "key": "Fabric Care",
      "value": "100% Polyester. hand Wash in cold Water. Dry in shade for Lasting Color.",
      "_id": {
        "$oid": "6370efb749ee88b1ea0fecd7"
      }
    },
    {
      "key": "Sleeve",
      "value": "Short Sleeve",
      "_id": {
        "$oid": "6370efb749ee88b1ea0fecd8"
      }
    }
  ],
  "price": 491,
  "images": [
    {
      "public_id": "thisissampleid",
      "url": "https://rukminim1.flixcart.com/image/832/832/xif0q/dress/z/e/h/m-gr5991-multi-harpa-original-imafutftght38gh6-bb.jpeg?q=70",
      "_id": {
        "$oid": "6370efb749ee88b1ea0fecdd"
      }
    },
    {
      "public_id": "thisissampleid",
      "url": "https://rukminim1.flixcart.com/image/832/832/ke1pnrk0/dress/z/e/h/xl-gr5991-multi-harpa-original-imafutfthqhy6ygg.jpeg?q=70",
      "_id": {
        "$oid": "6370efb749ee88b1ea0fecde"
      }
    },
    {
      "public_id": "thisissampleid",
      "url": "https://rukminim1.flixcart.com/image/832/832/ke1pnrk0/dress/z/e/h/m-gr5991-multi-harpa-original-imafutftcyhcke2v.jpeg?q=70",
      "_id": {
        "$oid": "6370efb749ee88b1ea0fecdf"
      }
    },
    {
      "public_id": "thisissampleid",
      "url": "https://rukminim1.flixcart.com/image/832/832/ke1pnrk0/dress/z/e/h/xl-gr5991-multi-harpa-original-imafutftqhsaa48s.jpeg?q=70",
      "_id": {
        "$oid": "6370efb749ee88b1ea0fece0"
      }
    },
    {
      "public_id": "thisissampleid",
      "url": "https://rukminim1.flixcart.com/image/832/832/ke1pnrk0/dress/z/e/h/m-gr5991-multi-harpa-original-imafutftpgymr48p.jpeg?q=70",
      "_id": {
        "$oid": "6370efb749ee88b1ea0fece1"
      }
    },
    {
      "public_id": "thisissampleid",
      "url": "https://rukminim1.flixcart.com/image/832/832/ke1pnrk0/dress/z/e/h/s-gr5991-multi-harpa-original-imafutftzdsv8jmd.jpeg?q=70",
      "_id": {
        "$oid": "6370efb749ee88b1ea0fece2"
      }
    }
  ],
  "category": "womenswear",
  "stock": 2,
  "numOfReviews": 3,
  "reviews": [
    {
      "user": {
        "$oid": "632564a90723f05096694c35"
      },
      "name": "Lathiya hardik",
      "rating": 4,
      "comment": "this product is amazing.Recently I have purchased it and to be honest i found it as worth it and must buy",
      "_id": {
        "$oid": "6364bf68ec919bc834cc5e7d"
      },
      "createdAt": {
        "$date": {
          "$numberLong": "1667546984959"
        }
      }
    },
    {
      "user": {
        "$oid": "6364c27bec919bc834cc5fb1"
      },
      "name": "Jay Rakholiya",
      "rating": 4,
      "comment": "this product is amazing.Recently I have purchased it and to be honest i found it as worth it and must buy",
      "_id": {
        "$oid": "6364c28eec919bc834cc5fc8"
      },
      "createdAt": {
        "$date": {
          "$numberLong": "1667893390129"
        }
      }
    },
    {
      "user": {
        "$oid": "63234f3b3df93eccd7c318f7"
      },
      "name": "Lathiya hardik",
      "comment": "this product is really awful",
      "_id": {
        "$oid": "6364c735ec919bc834cc61d4"
      },
      "createdAt": {
        "$date": {
          "$numberLong": "1667548981683"
        }
      },
      "rating": 2
    }
  ],
  "createdAt": {
    "$date": {
      "$numberLong": "1662884055476"
    }
  },
  "__v": 3,
  "sizes": [
    {
      "size": "S",
      "_id": {
        "$oid": "6370efb749ee88b1ea0fecd9"
      }
    },
    {
      "size": "M",
      "_id": {
        "$oid": "6370efb749ee88b1ea0fecda"
      }
    },
    {
      "size": "L",
      "_id": {
        "$oid": "6370efb749ee88b1ea0fecdb"
      }
    },
    {
      "size": "XL",
      "_id": {
        "$oid": "6370efb749ee88b1ea0fecdc"
      }
    }
  ],
  "discount": 75,
  "mrp": 1999,
  "brand": "HARPA",
  "seller": "HSAtlastradeFashion",
  "sellerRating": "4.7",
  "ratings": 3.3,
  "isFeatured": true
},{
  "_id": {
    "$oid": "631d98dbc8406ef6bfc2990d"
  },
  "name": "Regular Men Blue Jeans",
  "description": [
    {
      "key": "Style Code",
      "value": "LJ5205",
      "_id": {
        "$oid": "6371f357b9a06e32544262c6"
      }
    },
    {
      "key": "Ideal For",
      "value": "Men",
      "_id": {
        "$oid": "6371f357b9a06e32544262c7"
      }
    },
    {
      "key": "Suitable For",
      "value": "Western Wear",
      "_id": {
        "$oid": "6371f357b9a06e32544262c8"
      }
    },
    {
      "key": "Pack of",
      "value": "1",
      "_id": {
        "$oid": "6371f357b9a06e32544262c9"
      }
    },
    {
      "key": "Pocket Type",
      "value": "Patch Pocket",
      "_id": {
        "$oid": "6371f357b9a06e32544262ca"
      }
    },
    {
      "key": "Reversible",
      "value": "No",
      "_id": {
        "$oid": "6371f357b9a06e32544262cb"
      }
    },
    {
      "key": "Sales Package",
      "value": "1 Jeans",
      "_id": {
        "$oid": "6371f357b9a06e32544262cc"
      }
    },
    {
      "key": "Closure",
      "value": "Button",
      "_id": {
        "$oid": "6371f357b9a06e32544262cd"
      }
    },
    {
      "key": "Fabric",
      "value": "Denim",
      "_id": {
        "$oid": "6371f357b9a06e32544262ce"
      }
    },
    {
      "key": "Faded",
      "value": "Clean Look",
      "_id": {
        "$oid": "6371f357b9a06e32544262cf"
      }
    },
    {
      "key": "Rise",
      "value": "Mid Rise",
      "_id": {
        "$oid": "6371f357b9a06e32544262d0"
      }
    },
    {
      "key": "Distressed",
      "value": "Clean Look",
      "_id": {
        "$oid": "6371f357b9a06e32544262d1"
      }
    },
    {
      "key": "Stretchable",
      "value": "Yes",
      "_id": {
        "$oid": "6371f357b9a06e32544262d2"
      }
    },
    {
      "key": "Color",
      "value": "Blue",
      "_id": {
        "$oid": "6371f357b9a06e32544262d3"
      }
    },
    {
      "key": "Fly",
      "value": "Zipper",
      "_id": {
        "$oid": "6371f357b9a06e32544262d4"
      }
    },
    {
      "key": "Fabric Care",
      "value": "Machine Wash as per Tag, Do not Tumble Dry, Do not Iron on Print/Embroidery/Embellishment",
      "_id": {
        "$oid": "6371f357b9a06e32544262d5"
      }
    }
  ],
  "price": 359,
  "images": [
    {
      "public_id": "thisissampleid",
      "url": "https://rukminim1.flixcart.com/image/832/832/xif0q/jean/b/d/8/40-lj5205-lzard-original-imaggraxtwzmy2rd.jpeg?q=70",
      "_id": {
        "$oid": "6371f357b9a06e32544262d6"
      }
    },
    {
      "public_id": "thisissampleid",
      "url": "https://rukminim1.flixcart.com/image/832/832/xif0q/jean/o/l/i/40-lj5205-lzard-original-imaggraxhajs8x3q.jpeg?q=70",
      "_id": {
        "$oid": "6371f357b9a06e32544262d7"
      }
    },
    {
      "public_id": "thisissampleid",
      "url": "https://rukminim1.flixcart.com/image/832/832/xif0q/jean/j/z/8/40-lj5205-lzard-original-imaggraxxhgzgss7.jpeg?q=70",
      "_id": {
        "$oid": "6371f357b9a06e32544262d8"
      }
    },
    {
      "public_id": "thisissampleid",
      "url": "https://rukminim1.flixcart.com/image/832/832/xif0q/jean/q/r/q/40-lj5205-lzard-original-imaggraxastqgwjw.jpeg?q=70",
      "_id": {
        "$oid": "6371f357b9a06e32544262d9"
      }
    }
  ],
  "category": "menswear",
  "stock": 1,
  "numOfReviews": 0,
  "reviews": [],
  "createdAt": {
    "$date": {
      "$numberLong": "1662884059437"
    }
  },
  "__v": 0,
  "ratings": 0,
  "brand": "Lzard",
  "discount": 84,
  "isFeatured": true,
  "mrp": 2299,
  "seller": "RASSO",
  "sellerRating": "4",
  "sizes": [
    {
      "size": "28",
      "_id": {
        "$oid": "6371f357b9a06e32544262c1"
      }
    },
    {
      "size": "30",
      "_id": {
        "$oid": "6371f357b9a06e32544262c2"
      }
    },
    {
      "size": "32",
      "_id": {
        "$oid": "6371f357b9a06e32544262c3"
      }
    },
    {
      "size": "34",
      "_id": {
        "$oid": "6371f357b9a06e32544262c4"
      }
    },
    {
      "size": "36",
      "_id": {
        "$oid": "6371f357b9a06e32544262c5"
      }
    }
  ]
},{
  "_id": {
    "$oid": "631d98dfc8406ef6bfc29910"
  },
  "name": "Girls Calf Length Casual Dress  (Blue, 3/4 Sleeve)",
  "description": [
    {
      "key": "Style Code",
      "value": "GF0092-TEAL",
      "_id": {
        "$oid": "6371fff6bdd3489ab1d3c7b8"
      }
    },
    {
      "key": "Ideal For",
      "value": "Girls",
      "_id": {
        "$oid": "6371fff6bdd3489ab1d3c7b9"
      }
    },
    {
      "key": "Suitable For",
      "value": "Western Wear",
      "_id": {
        "$oid": "6371fff6bdd3489ab1d3c7ba"
      }
    },
    {
      "key": "Brand color",
      "value": "TEAL BLUE",
      "_id": {
        "$oid": "6371fff6bdd3489ab1d3c7bb"
      }
    },
    {
      "key": "Size",
      "value": "3 - 4 Years",
      "_id": {
        "$oid": "6371fff6bdd3489ab1d3c7bc"
      }
    },
    {
      "key": "Type",
      "value": "Ruffle Dress",
      "_id": {
        "$oid": "6371fff6bdd3489ab1d3c7bd"
      }
    },
    {
      "key": "Occasion",
      "value": "Casual",
      "_id": {
        "$oid": "6371fff6bdd3489ab1d3c7be"
      }
    },
    {
      "key": "Pattern",
      "value": "Self Design",
      "_id": {
        "$oid": "6371fff6bdd3489ab1d3c7bf"
      }
    },
    {
      "key": "Primary Color",
      "value": "Blue",
      "_id": {
        "$oid": "6371fff6bdd3489ab1d3c7c0"
      }
    },
    {
      "key": "Fabric",
      "value": "Crepe",
      "_id": {
        "$oid": "6371fff6bdd3489ab1d3c7c1"
      }
    },
    {
      "key": "Sleeve Type",
      "value": "3/4 Sleeve",
      "_id": {
        "$oid": "6371fff6bdd3489ab1d3c7c2"
      }
    },
    {
      "key": "Fabric Details",
      "value": "Crepe",
      "_id": {
        "$oid": "6371fff6bdd3489ab1d3c7c3"
      }
    }
  ],
  "price": 374,
  "rating": 0,
  "images": [
    {
      "public_id": "thisissampleid",
      "url": "https://rukminim1.flixcart.com/image/832/832/ky3b0y80/kids-dress/7/3/o/9-10-years-gf0092-teal-fashion-dream-original-imagaeh3zcg8gpxm.jpeg?q=70",
      "_id": {
        "$oid": "6371fff6bdd3489ab1d3c7c4"
      }
    },
    {
      "public_id": "thisissampleid",
      "url": "https://rukminim1.flixcart.com/image/832/832/ky3b0y80/kids-dress/g/y/m/9-10-years-gf0092-teal-fashion-dream-original-imagaeh3ypfu8ma7.jpeg?q=70",
      "_id": {
        "$oid": "6371fff6bdd3489ab1d3c7c5"
      }
    },
    {
      "public_id": "thisissampleid",
      "url": "https://rukminim1.flixcart.com/image/832/832/ky3b0y80/kids-dress/o/w/g/9-10-years-gf0092-teal-fashion-dream-original-imagaeh3afpzwcnh.jpeg?q=70",
      "_id": {
        "$oid": "6371fff6bdd3489ab1d3c7c6"
      }
    },
    {
      "public_id": "thisissampleid",
      "url": "https://rukminim1.flixcart.com/image/832/832/ky3b0y80/kids-dress/m/u/h/9-10-years-gf0092-teal-fashion-dream-original-imagaeh3ab8bf9cb.jpeg?q=70",
      "_id": {
        "$oid": "6371fff6bdd3489ab1d3c7c7"
      }
    },
    {
      "public_id": "thisissampleid",
      "url": "https://rukminim1.flixcart.com/image/832/832/ky3b0y80/kids-dress/o/s/a/9-10-years-gf0092-teal-fashion-dream-original-imagaeh3gmkj7zat.jpeg?q=70",
      "_id": {
        "$oid": "6371fff6bdd3489ab1d3c7c8"
      }
    }
  ],
  "category": "kidswear",
  "stock": 3,
  "numOfReviews": 0,
  "reviews": [],
  "createdAt": {
    "$date": {
      "$numberLong": "1662884063021"
    }
  },
  "__v": 0,
  "brand": "Fashion Dream",
  "discount": 76,
  "isFeatured": true,
  "mrp": 1599,
  "seller": "FashionDream",
  "sellerRating": "4.7",
  "sizes": [
    {
      "size": "3 - 4 years",
      "_id": {
        "$oid": "6371fff6bdd3489ab1d3c7b3"
      }
    },
    {
      "size": "7 - 8 years",
      "_id": {
        "$oid": "6371fff6bdd3489ab1d3c7b4"
      }
    },
    {
      "size": "9 - 10 years",
      "_id": {
        "$oid": "6371fff6bdd3489ab1d3c7b5"
      }
    },
    {
      "size": "11 - 12 years",
      "_id": {
        "$oid": "6371fff6bdd3489ab1d3c7b6"
      }
    },
    {
      "size": "13 - 14 years",
      "_id": {
        "$oid": "6371fff6bdd3489ab1d3c7b7"
      }
    }
  ]
},{
  "_id": {
    "$oid": "631d98e2c8406ef6bfc29913"
  },
  "name": "p5",
  "description": "this is good smartphone",
  "price": 26000,
  "rating": 0,
  "images": [
    {
      "public_id": "thisissampleid",
      "url": "product.jpg",
      "_id": {
        "$oid": "631d98e2c8406ef6bfc29914"
      }
    }
  ],
  "category": "cosmetics",
  "stock": 1,
  "numOfReviews": 0,
  "reviews": [],
  "createdAt": {
    "$date": {
      "$numberLong": "1662884066669"
    }
  },
  "__v": 0
},{
  "_id": {
    "$oid": "631d98e6c8406ef6bfc29916"
  },
  "name": "p6",
  "description": "this is good product",
  "price": 2000,
  "rating": 0,
  "images": [
    {
      "public_id": "thisissampleid",
      "url": "product.jpg",
      "_id": {
        "$oid": "631d98e6c8406ef6bfc29917"
      }
    }
  ],
  "category": "accessories",
  "stock": 1,
  "numOfReviews": 0,
  "reviews": [],
  "createdAt": {
    "$date": {
      "$numberLong": "1662884070625"
    }
  },
  "__v": 0
},{
  "_id": {
    "$oid": "631d98eac8406ef6bfc29919"
  },
  "name": "p7",
  "description": "this is good smartphone",
  "price": 26000,
  "rating": 0,
  "images": [
    {
      "public_id": "thisissampleid",
      "url": "product.jpg",
      "_id": {
        "$oid": "631d98eac8406ef6bfc2991a"
      }
    }
  ],
  "category": "smartphone",
  "stock": 1,
  "numOfReviews": 0,
  "reviews": [],
  "createdAt": {
    "$date": {
      "$numberLong": "1662884074551"
    }
  },
  "__v": 0
},{
  "_id": {
    "$oid": "631d98f0c8406ef6bfc2991c"
  },
  "name": "p8",
  "description": "this is good smartphone",
  "price": 26000,
  "rating": 0,
  "images": [
    {
      "public_id": "thisissampleid",
      "url": "product.jpg",
      "_id": {
        "$oid": "631d98f0c8406ef6bfc2991d"
      }
    }
  ],
  "category": "smartphone",
  "stock": 1,
  "numOfReviews": 0,
  "reviews": [],
  "createdAt": {
    "$date": {
      "$numberLong": "1662884080061"
    }
  },
  "__v": 0
},{
  "_id": {
    "$oid": "631d98f4c8406ef6bfc2991f"
  },
  "name": "p9",
  "description": "this is good smartphone",
  "price": 26000,
  "rating": 0,
  "images": [
    {
      "public_id": "thisissampleid",
      "url": "product.jpg",
      "_id": {
        "$oid": "631d98f4c8406ef6bfc29920"
      }
    }
  ],
  "category": "smartphone",
  "stock": 1,
  "numOfReviews": 0,
  "reviews": [],
  "createdAt": {
    "$date": {
      "$numberLong": "1662884084108"
    }
  },
  "__v": 0
},{
  "_id": {
    "$oid": "631d98f9c8406ef6bfc29922"
  },
  "name": "p10",
  "description": "this is good smartphone",
  "price": 26000,
  "rating": 0,
  "images": [
    {
      "public_id": "thisissampleid",
      "url": "product.jpg",
      "_id": {
        "$oid": "631d98f9c8406ef6bfc29923"
      }
    }
  ],
  "category": "smartphone",
  "stock": 1,
  "numOfReviews": 0,
  "reviews": [],
  "createdAt": {
    "$date": {
      "$numberLong": "1662884089137"
    }
  },
  "__v": 0
},{
  "_id": {
    "$oid": "6325751d5945cf15a434723f"
  },
  "name": "p11",
  "description": "this is good smartphone",
  "price": 26000,
  "ratings": 5,
  "images": [
    {
      "public_id": "thisissampleid",
      "url": "product.jpg",
      "_id": {
        "$oid": "6325751d5945cf15a4347240"
      }
    }
  ],
  "category": "smartphone",
  "stock": 0,
  "numOfReviews": 1,
  "user": {
    "$oid": "632564a90723f05096694c35"
  },
  "reviews": [
    {
      "user": {
        "$oid": "63234f3b3df93eccd7c318f7"
      },
      "name": "Lathiya hardik",
      "rating": 5,
      "comment": "this product is fabulous",
      "_id": {
        "$oid": "6325843fe13795d205461701"
      }
    }
  ],
  "createdAt": {
    "$date": {
      "$numberLong": "1663399197074"
    }
  },
  "__v": 2
}]